setup.py
Shelves.egg-info/PKG-INFO
Shelves.egg-info/SOURCES.txt
Shelves.egg-info/dependency_links.txt
Shelves.egg-info/top_level.txt
shelves/__init__.py
shelves/boxes/__init__.py
shelves/boxes/box.py
shelves/boxes/file.py
shelves/boxes/remote.py
shelves/boxes/tahoe.py
shelves/schemas/__init__.py
shelves/schemas/basic.py
shelves/shelves/__init__.py
shelves/shelves/file.py
shelves/shelves/shelf.py