Metadata-Version: 1.1
Name: Shelves
Version: 0.3.7
Summary: Shelves to store Box of documents in the brodacast-system
Home-page: https://git.leloop.org/broadcast-system/shelves
Author: Okhin
Author-email: okhin@okhin.fr
License: UNKNOWN
Platform: UNKNOWN
Requires: tahoe_whoosh
Requires: whoosh
Requires: requests
